[{"id": 0, "source": "donald", "target": "trump", "size": 17.0}, {"id": 1, "source": "incendie", "target": "aude", "size": 12.0}, {"id": 2, "source": "degré", "target": "c", "size": 11.0}, {"id": 3, "source": "droit", "target": "douane", "size": 10.0}, {"id": 4, "source": "guerre", "target": "ukraine", "size": 10.0}, {"id": 5, "source": "vigilance", "target": "rouge", "size": 10.0}, {"id": 6, "source": "canicule", "target": "département", "size": 9.0}, {"id": 7, "source": "suppression", "target": "jour", "size": 9.0}, {"id": 8, "source": "département", "target": "vigilance", "size": 8.0}, {"id": 9, "source": "trump", "target": "poutine", "size": 8.0}, {"id": 10, "source": "rouge", "target": "mardi", "size": 6.999999999999999}, {"id": 11, "source": "assurance", "target": "chômage", "size": 6.0}, {"id": 12, "source": "canicule", "target": "france", "size": 6.0}, {"id": 13, "source": "garde", "target": "washington", "size": 6.0}, {"id": 14, "source": "c", "target": "bordeaux", "size": 5.0}, {"id": 15, "source": "ferrand", "target": "prévot", "size": 5.0}, {"id": 16, "source": "pauline", "target": "ferrand", "size": 5.0}, {"id": 17, "source": "vladimir", "target": "poutine", "size": 5.0}, {"id": 18, "source": "centrale", "target": "gravelines", "size": 4.0}, {"id": 19, "source": "déploiement", "target": "garde", "size": 4.0}, {"id": 20, "source": "hectare", "target": "végétation", "size": 4.0}, {"id": 21, "source": "journaliste", "target": "gaza", "size": 4.0}, {"id": 22, "source": "maire", "target": "isère", "size": 4.0}, {"id": 23, "source": "point", "target": "situation", "size": 4.0}, {"id": 24, "source": "record", "target": "chaleur", "size": 4.0}, {"id": 25, "source": "sommet", "target": "trump", "size": 4.0}, {"id": 26, "source": "trump", "target": "déploiement", "size": 4.0}, {"id": 27, "source": "vague", "target": "chaleur", "size": 4.0}, {"id": 28, "source": "william", "target": "thay", "size": 4.0}, {"id": 29, "source": "andras", "target": "pandy", "size": 3.0}, {"id": 30, "source": "arrêt", "target": "centrale", "size": 3.0}, {"id": 31, "source": "bordeaux", "target": "record", "size": 3.0}, {"id": 32, "source": "contrôle", "target": "ville", "size": 3.0}, {"id": 33, "source": "françois", "target": "bayrou", "size": 3.0}, {"id": 34, "source": "gaza", "target": "anas", "size": 3.0}, {"id": 35, "source": "guerre", "target": "france", "size": 3.0}, {"id": 36, "source": "guerre", "target": "gaza", "size": 3.0}, {"id": 37, "source": "lundi", "target": "août", "size": 3.0}, {"id": 38, "source": "pandy", "target": "pasteur", "size": 3.0}, {"id": 39, "source": "plan", "target": "gaza", "size": 3.0}, {"id": 40, "source": "poutine", "target": "alaska", "size": 3.0}, {"id": 41, "source": "record", "target": "température", "size": 3.0}, {"id": 42, "source": "rencontre", "target": "trump", "size": 3.0}, {"id": 43, "source": "risque", "target": "guerre", "size": 3.0}, {"id": 44, "source": "royaume", "target": "uni", "size": 3.0}, {"id": 45, "source": "réforme", "target": "assurance", "size": 3.0}, {"id": 46, "source": "température", "target": "degré", "size": 3.0}, {"id": 47, "source": "tour", "target": "france", "size": 3.0}, {"id": 48, "source": "vigilance", "target": "orange", "size": 3.0}, {"id": 49, "source": "ville", "target": "gaza", "size": 3.0}, {"id": 50, "source": "week", "target": "end", "size": 3.0}, {"id": 51, "source": "xi", "target": "jinping", "size": 3.0}, {"id": 52, "source": "agression", "target": "maire", "size": 2.0}, {"id": 53, "source": "anas", "target": "sharif", "size": 2.0}, {"id": 54, "source": "aude", "target": "feu", "size": 2.0}, {"id": 55, "source": "aude", "target": "hectare", "size": 2.0}, {"id": 56, "source": "aude", "target": "vent", "size": 2.0}, {"id": 57, "source": "canicule", "target": "toulouse", "size": 2.0}, {"id": 58, "source": "censure", "target": "loi", "size": 2.0}, {"id": 59, "source": "centrale", "target": "europe", "size": 2.0}, {"id": 60, "source": "chaleur", "target": "lundi", "size": 2.0}, {"id": 61, "source": "charente", "target": "hectare", "size": 2.0}, {"id": 62, "source": "chômage", "target": "suppression", "size": 2.0}, {"id": 63, "source": "douane", "target": "donald", "size": 2.0}, {"id": 64, "source": "douane", "target": "trump", "size": 2.0}, {"id": 65, "source": "département", "target": "alerte", "size": 2.0}, {"id": 66, "source": "etats-unis", "target": "russie", "size": 2.0}, {"id": 67, "source": "explosion", "target": "usine", "size": 2.0}, {"id": 68, "source": "face", "target": "canicule", "size": 2.0}, {"id": 69, "source": "face", "target": "trump", "size": 2.0}, {"id": 70, "source": "gaza", "target": "emmanuel", "size": 2.0}, {"id": 71, "source": "gaza", "target": "journaliste", "size": 2.0}, {"id": 72, "source": "gravelines", "target": "centrale", "size": 2.0}, {"id": 73, "source": "homme", "target": "femme", "size": 2.0}, {"id": 74, "source": "info", "target": "week", "size": 2.0}, {"id": 75, "source": "israël", "target": "contrôle", "size": 2.0}, {"id": 76, "source": "isère", "target": "maire", "size": 2.0}, {"id": 77, "source": "jour", "target": "alsace", "size": 2.0}, {"id": 78, "source": "journaliste", "target": "al", "size": 2.0}, {"id": 79, "source": "journée", "target": "lundi", "size": 2.0}, {"id": 80, "source": "mardi", "target": "midi", "size": 2.0}, {"id": 81, "source": "milliard", "target": "euro", "size": 2.0}, {"id": 82, "source": "mise", "target": "arrêt", "size": 2.0}, {"id": 83, "source": "mise", "target": "garde", "size": 2.0}, {"id": 84, "source": "méduse", "target": "arrêt", "size": 2.0}, {"id": 85, "source": "occupation", "target": "gaza", "size": 2.0}, {"id": 86, "source": "pasteur", "target": "récit", "size": 2.0}, {"id": 87, "source": "prévot", "target": "tour", "size": 2.0}, {"id": 88, "source": "rencontre", "target": "vladimir", "size": 2.0}, {"id": 89, "source": "rouge", "target": "vigilance", "size": 2.0}, {"id": 90, "source": "réunion", "target": "mercredi", "size": 2.0}, {"id": 91, "source": "sharif", "target": "journaliste", "size": 2.0}, {"id": 92, "source": "sommet", "target": "donald", "size": 2.0}, {"id": 93, "source": "sud-ouest", "target": "vigilance", "size": 2.0}, {"id": 94, "source": "température", "target": "lundi", "size": 2.0}, {"id": 95, "source": "trump", "target": "russie", "size": 2.0}, {"id": 96, "source": "trump", "target": "vladimir", "size": 2.0}, {"id": 97, "source": "ukraine", "target": "jour", "size": 2.0}, {"id": 98, "source": "ukraine", "target": "trump", "size": 2.0}, {"id": 99, "source": "végétation", "target": "feu", "size": 2.0}, {"id": 100, "source": "yi", "target": "yi", "size": 2.0}, {"id": 101, "source": "états-unis", "target": "trump", "size": 2.0}, {"id": 102, "source": "accord", "target": "etats-unis", "size": 1.0}, {"id": 103, "source": "accord", "target": "paix", "size": 1.0}, {"id": 104, "source": "accord", "target": "personne", "size": 1.0}, {"id": 105, "source": "action", "target": "question", "size": 1.0}, {"id": 106, "source": "acétamipride", "target": "conseil", "size": 1.0}, {"id": 107, "source": "acétamipride", "target": "france", "size": 1.0}, {"id": 108, "source": "affaire", "target": "début", "size": 1.0}, {"id": 109, "source": "afp", "target": "journaliste", "size": 1.0}, {"id": 110, "source": "afp", "target": "prix", "size": 1.0}, {"id": 111, "source": "agression", "target": "femme", "size": 1.0}, {"id": 112, "source": "al", "target": "sharif", "size": 1.0}, {"id": 113, "source": "alaska", "target": "donald", "size": 1.0}, {"id": 114, "source": "alaska", "target": "ukraine", "size": 1.0}, {"id": 115, "source": "alaska", "target": "victoire", "size": 1.0}, {"id": 116, "source": "alerte", "target": "face", "size": 1.0}, {"id": 117, "source": "alerte", "target": "mardi", "size": 1.0}, {"id": 118, "source": "alerte", "target": "niveau", "size": 1.0}, {"id": 119, "source": "alsace", "target": "autorité", "size": 1.0}, {"id": 120, "source": "amour", "target": "mort", "size": 1.0}, {"id": 121, "source": "ampleur", "target": "incendie", "size": 1.0}, {"id": 122, "source": "américain", "target": "hiroshima", "size": 1.0}, {"id": 123, "source": "an", "target": "balle", "size": 1.0}, {"id": 124, "source": "an", "target": "explosion", "size": 1.0}, {"id": 125, "source": "an", "target": "histoire", "size": 1.0}, {"id": 126, "source": "an", "target": "mort", "size": 1.0}, {"id": 127, "source": "an", "target": "travail", "size": 1.0}, {"id": 128, "source": "anas", "target": "al", "size": 1.0}, {"id": 129, "source": "année", "target": "guerre", "size": 1.0}, {"id": 130, "source": "août", "target": "américain", "size": 1.0}, {"id": 131, "source": "arme", "target": "service", "size": 1.0}, {"id": 132, "source": "arme", "target": "ukraine", "size": 1.0}, {"id": 133, "source": "armée", "target": "washington", "size": 1.0}, {"id": 134, "source": "arrêt", "target": "cause", "size": 1.0}, {"id": 135, "source": "arrêt", "target": "méduse", "size": 1.0}, {"id": 136, "source": "aude", "target": "canicule", "size": 1.0}, {"id": 137, "source": "aude", "target": "habitant", "size": 1.0}, {"id": 138, "source": "aude", "target": "incendie", "size": 1.0}, {"id": 139, "source": "autorité", "target": "alerte", "size": 1.0}, {"id": 140, "source": "autorité", "target": "journée", "size": 1.0}, {"id": 141, "source": "autorité", "target": "projet", "size": 1.0}, {"id": 142, "source": "autoroute", "target": "place", "size": 1.0}, {"id": 143, "source": "balle", "target": "voiture", "size": 1.0}, {"id": 144, "source": "bayrou", "target": "place", "size": 1.0}, {"id": 145, "source": "bayrou", "target": "économie", "size": 1.0}, {"id": 146, "source": "billet", "target": "festival", "size": 1.0}, {"id": 147, "source": "billet", "target": "édition", "size": 1.0}, {"id": 148, "source": "blessé", "target": "point", "size": 1.0}, {"id": 149, "source": "bordeaux", "target": "canicule", "size": 1.0}, {"id": 150, "source": "bordeaux", "target": "degré", "size": 1.0}, {"id": 151, "source": "bordeaux", "target": "toulouse", "size": 1.0}, {"id": 152, "source": "c", "target": "jour", "size": 1.0}, {"id": 153, "source": "c", "target": "nuit", "size": 1.0}, {"id": 154, "source": "canicule", "target": "face", "size": 1.0}, {"id": 155, "source": "canicule", "target": "gouvernement", "size": 1.0}, {"id": 156, "source": "canicule", "target": "journaliste", "size": 1.0}, {"id": 157, "source": "canicule", "target": "mer", "size": 1.0}, {"id": 158, "source": "canicule", "target": "niveau", "size": 1.0}, {"id": 159, "source": "canicule", "target": "personne", "size": 1.0}, {"id": 160, "source": "canicule", "target": "pollution", "size": 1.0}, {"id": 161, "source": "canicule", "target": "record", "size": 1.0}, {"id": 162, "source": "canicule", "target": "rencontre", "size": 1.0}, {"id": 163, "source": "canicule", "target": "sud", "size": 1.0}, {"id": 164, "source": "cauchemar", "target": "habitant", "size": 1.0}, {"id": 165, "source": "cauchemar", "target": "suisse", "size": 1.0}, {"id": 166, "source": "cause", "target": "groupe", "size": 1.0}, {"id": 167, "source": "cause", "target": "méduse", "size": 1.0}, {"id": 168, "source": "cause", "target": "risque", "size": 1.0}, {"id": 169, "source": "cause", "target": "voyage", "size": 1.0}, {"id": 170, "source": "censure", "target": "acétamipride", "size": 1.0}, {"id": 171, "source": "censure", "target": "proche", "size": 1.0}, {"id": 172, "source": "centrale", "target": "cause", "size": 1.0}, {"id": 173, "source": "chaleur", "target": "france", "size": 1.0}, {"id": 174, "source": "chaleur", "target": "niveau", "size": 1.0}, {"id": 175, "source": "chaleur", "target": "sud-ouest", "size": 1.0}, {"id": 176, "source": "chaleur", "target": "week", "size": 1.0}, {"id": 177, "source": "champignon", "target": "tentative", "size": 1.0}, {"id": 178, "source": "charente", "target": "pompier", "size": 1.0}, {"id": 179, "source": "chine", "target": "armée", "size": 1.0}, {"id": 180, "source": "chine", "target": "bras", "size": 1.0}, {"id": 181, "source": "chine", "target": "donald", "size": 1.0}, {"id": 182, "source": "chine", "target": "face", "size": 1.0}, {"id": 183, "source": "chute", "target": "concert", "size": 1.0}, {"id": 184, "source": "chute", "target": "mur", "size": 1.0}, {"id": 185, "source": "chômage", "target": "gouvernement", "size": 1.0}, {"id": 186, "source": "chômage", "target": "piste", "size": 1.0}, {"id": 187, "source": "chômage", "target": "état", "size": 1.0}, {"id": 188, "source": "cinéma", "target": "femme", "size": 1.0}, {"id": 189, "source": "cinéma", "target": "vie", "size": 1.0}, {"id": 190, "source": "combat", "target": "liberté", "size": 1.0}, {"id": 191, "source": "concert", "target": "femme", "size": 1.0}, {"id": 192, "source": "concert", "target": "palestine", "size": 1.0}, {"id": 193, "source": "concert", "target": "temps", "size": 1.0}, {"id": 194, "source": "condition", "target": "femme", "size": 1.0}, {"id": 195, "source": "condition", "target": "météo", "size": 1.0}, {"id": 196, "source": "conquête", "target": "gaza", "size": 1.0}, {"id": 197, "source": "conquête", "target": "mars", "size": 1.0}, {"id": 198, "source": "conseil", "target": "censure", "size": 1.0}, {"id": 199, "source": "degré", "target": "dimanche", "size": 1.0}, {"id": 200, "source": "degré", "target": "lundi", "size": 1.0}, {"id": 201, "source": "dimanche", "target": "point", "size": 1.0}, {"id": 202, "source": "diplomatie", "target": "ue", "size": 1.0}, {"id": 203, "source": "direct", "target": "canicule", "size": 1.0}, {"id": 204, "source": "direct", "target": "gaza", "size": 1.0}, {"id": 205, "source": "direct", "target": "guerre", "size": 1.0}, {"id": 206, "source": "douane", "target": "chine", "size": 1.0}, {"id": 207, "source": "douane", "target": "france", "size": 1.0}, {"id": 208, "source": "douane", "target": "réunion", "size": 1.0}, {"id": 209, "source": "début", "target": "année", "size": 1.0}, {"id": 210, "source": "département", "target": "rouge", "size": 1.0}, {"id": 211, "source": "département", "target": "sud-ouest", "size": 1.0}, {"id": 212, "source": "eau", "target": "méduse", "size": 1.0}, {"id": 213, "source": "emmanuel", "target": "plan", "size": 1.0}, {"id": 214, "source": "emploi", "target": "usine", "size": 1.0}, {"id": 215, "source": "emprise", "target": "femme", "size": 1.0}, {"id": 216, "source": "end", "target": "août", "size": 1.0}, {"id": 217, "source": "entrée", "target": "vie", "size": 1.0}, {"id": 218, "source": "etats-unis", "target": "droit", "size": 1.0}, {"id": 219, "source": "etats-unis", "target": "hiroshima", "size": 1.0}, {"id": 220, "source": "etats-unis", "target": "négociation", "size": 1.0}, {"id": 221, "source": "euro", "target": "an", "size": 1.0}, {"id": 222, "source": "euro", "target": "police", "size": 1.0}, {"id": 223, "source": "euro", "target": "économie", "size": 1.0}, {"id": 224, "source": "europe", "target": "france", "size": 1.0}, {"id": 225, "source": "europe", "target": "mise", "size": 1.0}, {"id": 226, "source": "europe", "target": "vague", "size": 1.0}, {"id": 227, "source": "européen", "target": "jeu", "size": 1.0}, {"id": 228, "source": "européen", "target": "ukraine", "size": 1.0}, {"id": 229, "source": "européen", "target": "zelensky", "size": 1.0}, {"id": 230, "source": "face", "target": "affaire", "size": 1.0}, {"id": 231, "source": "face", "target": "ampleur", "size": 1.0}, {"id": 232, "source": "face", "target": "chaleur", "size": 1.0}, {"id": 233, "source": "face", "target": "histoire", "size": 1.0}, {"id": 234, "source": "face", "target": "ia", "size": 1.0}, {"id": 235, "source": "face", "target": "justice", "size": 1.0}, {"id": 236, "source": "face", "target": "plan", "size": 1.0}, {"id": 237, "source": "face", "target": "réforme", "size": 1.0}, {"id": 238, "source": "fact", "target": "afp", "size": 1.0}, {"id": 239, "source": "fact", "target": "journée", "size": 1.0}, {"id": 240, "source": "fact", "target": "travail", "size": 1.0}, {"id": 241, "source": "famille", "target": "an", "size": 1.0}, {"id": 242, "source": "femme", "target": "an", "size": 1.0}, {"id": 243, "source": "femme", "target": "bébé", "size": 1.0}, {"id": 244, "source": "femme", "target": "enfant", "size": 1.0}, {"id": 245, "source": "femme", "target": "justice", "size": 1.0}, {"id": 246, "source": "ferrand", "target": "face", "size": 1.0}, {"id": 247, "source": "festival", "target": "édition", "size": 1.0}, {"id": 248, "source": "feu", "target": "autorité", "size": 1.0}, {"id": 249, "source": "feu", "target": "charente", "size": 1.0}, {"id": 250, "source": "feu", "target": "dimanche", "size": 1.0}, {"id": 251, "source": "feu", "target": "europe", "size": 1.0}, {"id": 252, "source": "feu", "target": "forêt", "size": 1.0}, {"id": 253, "source": "fiction", "target": "combat", "size": 1.0}, {"id": 254, "source": "film", "target": "meghan", "size": 1.0}, {"id": 255, "source": "film", "target": "semaine", "size": 1.0}, {"id": 256, "source": "film", "target": "série", "size": 1.0}, {"id": 257, "source": "fils", "target": "air", "size": 1.0}, {"id": 258, "source": "fils", "target": "suisse", "size": 1.0}, {"id": 259, "source": "fils", "target": "élu", "size": 1.0}, {"id": 260, "source": "fin", "target": "guerre", "size": 1.0}, {"id": 261, "source": "fin", "target": "septembre", "size": 1.0}, {"id": 262, "source": "fin", "target": "série", "size": 1.0}, {"id": 263, "source": "fois", "target": "mois", "size": 1.0}, {"id": 264, "source": "fois", "target": "personne", "size": 1.0}, {"id": 265, "source": "fois", "target": "tour", "size": 1.0}, {"id": 266, "source": "football", "target": "fc", "size": 1.0}, {"id": 267, "source": "football", "target": "feu", "size": 1.0}, {"id": 268, "source": "forêt", "target": "flamme", "size": 1.0}, {"id": 269, "source": "france", "target": "année", "size": 1.0}, {"id": 270, "source": "france", "target": "degré", "size": 1.0}, {"id": 271, "source": "france", "target": "département", "size": 1.0}, {"id": 272, "source": "france", "target": "emmanuel", "size": 1.0}, {"id": 273, "source": "france", "target": "enfant", "size": 1.0}, {"id": 274, "source": "france", "target": "jeu", "size": 1.0}, {"id": 275, "source": "france", "target": "plan", "size": 1.0}, {"id": 276, "source": "france", "target": "pluie", "size": 1.0}, {"id": 277, "source": "france", "target": "record", "size": 1.0}, {"id": 278, "source": "france", "target": "région", "size": 1.0}, {"id": 279, "source": "france", "target": "température", "size": 1.0}, {"id": 280, "source": "france", "target": "william", "size": 1.0}, {"id": 281, "source": "garde", "target": "face", "size": 1.0}, {"id": 282, "source": "garde", "target": "poutine", "size": 1.0}, {"id": 283, "source": "garde", "target": "zelensky", "size": 1.0}, {"id": 284, "source": "gaza", "target": "frappe", "size": 1.0}, {"id": 285, "source": "gaza", "target": "israël", "size": 1.0}, {"id": 286, "source": "gaza", "target": "jour", "size": 1.0}, {"id": 287, "source": "gaza", "target": "mur", "size": 1.0}, {"id": 288, "source": "gaza", "target": "netanyahou", "size": 1.0}, {"id": 289, "source": "gaza", "target": "plan", "size": 1.0}, {"id": 290, "source": "gaza", "target": "réunion", "size": 1.0}, {"id": 291, "source": "geste", "target": "face", "size": 1.0}, {"id": 292, "source": "geste", "target": "origine", "size": 1.0}, {"id": 293, "source": "gouvernement", "target": "geste", "size": 1.0}, {"id": 294, "source": "gouvernement", "target": "milliard", "size": 1.0}, {"id": 295, "source": "gravelines", "target": "arrêt", "size": 1.0}, {"id": 296, "source": "gravelines", "target": "méduse", "size": 1.0}, {"id": 297, "source": "groupe", "target": "action", "size": 1.0}, {"id": 298, "source": "groupe", "target": "méduse", "size": 1.0}, {"id": 299, "source": "guerre", "target": "chine", "size": 1.0}, {"id": 300, "source": "guerre", "target": "journaliste", "size": 1.0}, {"id": 301, "source": "guerre", "target": "trump", "size": 1.0}, {"id": 302, "source": "habitant", "target": "région", "size": 1.0}, {"id": 303, "source": "harry", "target": "meghan", "size": 1.0}, {"id": 304, "source": "hectare", "target": "charente", "size": 1.0}, {"id": 305, "source": "hectare", "target": "jour", "size": 1.0}, {"id": 306, "source": "hectare", "target": "pompier", "size": 1.0}, {"id": 307, "source": "heure", "target": "recherche", "size": 1.0}, {"id": 308, "source": "heure", "target": "trump", "size": 1.0}, {"id": 309, "source": "histoire", "target": "droit", "size": 1.0}, {"id": 310, "source": "histoire", "target": "gaza", "size": 1.0}, {"id": 311, "source": "histoire", "target": "trudy", "size": 1.0}, {"id": 312, "source": "homme", "target": "an", "size": 1.0}, {"id": 313, "source": "homme", "target": "balle", "size": 1.0}, {"id": 314, "source": "homme", "target": "chute", "size": 1.0}, {"id": 315, "source": "homme", "target": "droit", "size": 1.0}, {"id": 316, "source": "homme", "target": "maire", "size": 1.0}, {"id": 317, "source": "homme", "target": "mère", "size": 1.0}, {"id": 318, "source": "ia", "target": "titre", "size": 1.0}, {"id": 319, "source": "ia", "target": "trump", "size": 1.0}, {"id": 320, "source": "incendie", "target": "ampleur", "size": 1.0}, {"id": 321, "source": "incendie", "target": "charente", "size": 1.0}, {"id": 322, "source": "incendie", "target": "habitant", "size": 1.0}, {"id": 323, "source": "incendie", "target": "hectare", "size": 1.0}, {"id": 324, "source": "incendie", "target": "italie", "size": 1.0}, {"id": 325, "source": "incendie", "target": "risque", "size": 1.0}, {"id": 326, "source": "info", "target": "midi", "size": 1.0}, {"id": 327, "source": "intérêt", "target": "intérêt", "size": 1.0}, {"id": 328, "source": "israël", "target": "plan", "size": 1.0}, {"id": 329, "source": "isère", "target": "vigilance", "size": 1.0}, {"id": 330, "source": "jeu", "target": "pauline", "size": 1.0}, {"id": 331, "source": "jinping", "target": "diplomatie", "size": 1.0}, {"id": 332, "source": "jinping", "target": "homme", "size": 1.0}, {"id": 333, "source": "jinping", "target": "mois", "size": 1.0}, {"id": 334, "source": "jour", "target": "fiction", "size": 1.0}, {"id": 335, "source": "jour", "target": "france", "size": 1.0}, {"id": 336, "source": "jour", "target": "françois", "size": 1.0}, {"id": 337, "source": "jour", "target": "gouvernement", "size": 1.0}, {"id": 338, "source": "jour", "target": "homme", "size": 1.0}, {"id": 339, "source": "jour", "target": "journée", "size": 1.0}, {"id": 340, "source": "jour", "target": "situation", "size": 1.0}, {"id": 341, "source": "jour", "target": "syndicat", "size": 1.0}, {"id": 342, "source": "journal", "target": "11/08/2025", "size": 1.0}, {"id": 343, "source": "journaliste", "target": "afp", "size": 1.0}, {"id": 344, "source": "journaliste", "target": "armée", "size": 1.0}, {"id": 345, "source": "journaliste", "target": "fact", "size": 1.0}, {"id": 346, "source": "journaliste", "target": "israël", "size": 1.0}, {"id": 347, "source": "journée", "target": "fact", "size": 1.0}, {"id": 348, "source": "loi", "target": "conseil", "size": 1.0}, {"id": 349, "source": "loi", "target": "état", "size": 1.0}, {"id": 350, "source": "lundi", "target": "semaine", "size": 1.0}, {"id": 351, "source": "lundi", "target": "sud-ouest", "size": 1.0}, {"id": 352, "source": "lundi", "target": "ville", "size": 1.0}, {"id": 353, "source": "maire", "target": "village", "size": 1.0}, {"id": 354, "source": "mardi", "target": "août", "size": 1.0}, {"id": 355, "source": "mardi", "target": "bordeaux", "size": 1.0}, {"id": 356, "source": "mardi", "target": "chaleur", "size": 1.0}, {"id": 357, "source": "marin", "target": "eau", "size": 1.0}, {"id": 358, "source": "mars", "target": "prix", "size": 1.0}, {"id": 359, "source": "meghan", "target": "harry", "size": 1.0}, {"id": 360, "source": "meghan", "target": "projet", "size": 1.0}, {"id": 361, "source": "mer", "target": "maison", "size": 1.0}, {"id": 362, "source": "mercato", "target": "accord", "size": 1.0}, {"id": 363, "source": "mercato", "target": "psg", "size": 1.0}, {"id": 364, "source": "mercredi", "target": "donald", "size": 1.0}, {"id": 365, "source": "mercredi", "target": "européen", "size": 1.0}, {"id": 366, "source": "mercredi", "target": "saison", "size": 1.0}, {"id": 367, "source": "mercredi", "target": "trump", "size": 1.0}, {"id": 368, "source": "mesure", "target": "plan", "size": 1.0}, {"id": 369, "source": "meurtre", "target": "espagne", "size": 1.0}, {"id": 370, "source": "meurtre", "target": "journaliste", "size": 1.0}, {"id": 371, "source": "microplastique", "target": "air", "size": 1.0}, {"id": 372, "source": "microplastique", "target": "eau", "size": 1.0}, {"id": 373, "source": "migrant", "target": "maroc", "size": 1.0}, {"id": 374, "source": "millier", "target": "mort", "size": 1.0}, {"id": 375, "source": "million", "target": "euro", "size": 1.0}, {"id": 376, "source": "million", "target": "habitant", "size": 1.0}, {"id": 377, "source": "million", "target": "heure", "size": 1.0}, {"id": 378, "source": "mois", "target": "baignade", "size": 1.0}, {"id": 379, "source": "mois", "target": "bras", "size": 1.0}, {"id": 380, "source": "monde", "target": "accord", "size": 1.0}, {"id": 381, "source": "monde", "target": "star", "size": 1.0}, {"id": 382, "source": "mort", "target": "blessé", "size": 1.0}, {"id": 383, "source": "mort", "target": "combat", "size": 1.0}, {"id": 384, "source": "mère", "target": "aide", "size": 1.0}, {"id": 385, "source": "méduse", "target": "mise", "size": 1.0}, {"id": 386, "source": "mémoire", "target": "arme", "size": 1.0}, {"id": 387, "source": "netanyahou", "target": "aide", "size": 1.0}, {"id": 388, "source": "netanyahou", "target": "travail", "size": 1.0}, {"id": 389, "source": "niveau", "target": "sud", "size": 1.0}, {"id": 390, "source": "niveau", "target": "sud-ouest", "size": 1.0}, {"id": 391, "source": "notre-dame", "target": "emprise", "size": 1.0}, {"id": 392, "source": "notre-dame", "target": "paris", "size": 1.0}, {"id": 393, "source": "novasco", "target": "fin", "size": 1.0}, {"id": 394, "source": "nuit", "target": "région", "size": 1.0}, {"id": 395, "source": "nuit", "target": "vague", "size": 1.0}, {"id": 396, "source": "négociation", "target": "entrée", "size": 1.0}, {"id": 397, "source": "négociation", "target": "suisse", "size": 1.0}, {"id": 398, "source": "orange", "target": "canicule", "size": 1.0}, {"id": 399, "source": "orange", "target": "mardi", "size": 1.0}, {"id": 400, "source": "orange", "target": "température", "size": 1.0}, {"id": 401, "source": "paix", "target": "washington", "size": 1.0}, {"id": 402, "source": "palestine", "target": "action", "size": 1.0}, {"id": 403, "source": "paris", "target": "fc", "size": 1.0}, {"id": 404, "source": "paris", "target": "homme", "size": 1.0}, {"id": 405, "source": "paris", "target": "jour", "size": 1.0}, {"id": 406, "source": "paris", "target": "touriste", "size": 1.0}, {"id": 407, "source": "piste", "target": "françois", "size": 1.0}, {"id": 408, "source": "place", "target": "europe", "size": 1.0}, {"id": 409, "source": "place", "target": "point", "size": 1.0}, {"id": 410, "source": "plan", "target": "conquête", "size": 1.0}, {"id": 411, "source": "plan", "target": "netanyahou", "size": 1.0}, {"id": 412, "source": "plan", "target": "occupation", "size": 1.0}, {"id": 413, "source": "plan", "target": "suppression", "size": 1.0}, {"id": 414, "source": "plan", "target": "trump", "size": 1.0}, {"id": 415, "source": "pluie", "target": "million", "size": 1.0}, {"id": 416, "source": "point", "target": "incendie", "size": 1.0}, {"id": 417, "source": "point", "target": "vague", "size": 1.0}, {"id": 418, "source": "police", "target": "baignade", "size": 1.0}, {"id": 419, "source": "police", "target": "fin", "size": 1.0}, {"id": 420, "source": "police", "target": "fois", "size": 1.0}, {"id": 421, "source": "pollution", "target": "négociation", "size": 1.0}, {"id": 422, "source": "pompier", "target": "point", "size": 1.0}, {"id": 423, "source": "pompier", "target": "travail", "size": 1.0}, {"id": 424, "source": "poutine", "target": "11/08", "size": 1.0}, {"id": 425, "source": "poutine", "target": "août", "size": 1.0}, {"id": 426, "source": "poutine", "target": "info", "size": 1.0}, {"id": 427, "source": "poutine", "target": "paix", "size": 1.0}, {"id": 428, "source": "poutine", "target": "ukraine", "size": 1.0}, {"id": 429, "source": "poutine", "target": "victoire", "size": 1.0}, {"id": 430, "source": "poutine", "target": "zelensky", "size": 1.0}, {"id": 431, "source": "pression", "target": "pression", "size": 1.0}, {"id": 432, "source": "prix", "target": "projet", "size": 1.0}, {"id": 433, "source": "proche", "target": "victime", "size": 1.0}, {"id": 434, "source": "projet", "target": "autoroute", "size": 1.0}, {"id": 435, "source": "projet", "target": "bayrou", "size": 1.0}, {"id": 436, "source": "projet", "target": "film", "size": 1.0}, {"id": 437, "source": "projet", "target": "françois", "size": 1.0}, {"id": 438, "source": "psg", "target": "paris", "size": 1.0}, {"id": 439, "source": "question", "target": "rencontre", "size": 1.0}, {"id": 440, "source": "raison", "target": "record", "size": 1.0}, {"id": 441, "source": "raison", "target": "température", "size": 1.0}, {"id": 442, "source": "regard", "target": "homme", "size": 1.0}, {"id": 443, "source": "regard", "target": "regard", "size": 1.0}, {"id": 444, "source": "rodriguez", "target": "fc", "size": 1.0}, {"id": 445, "source": "rouge", "target": "11/08", "size": 1.0}, {"id": 446, "source": "rouge", "target": "guerre", "size": 1.0}, {"id": 447, "source": "russie", "target": "semaine", "size": 1.0}, {"id": 448, "source": "russie", "target": "trump", "size": 1.0}, {"id": 449, "source": "russie", "target": "victoire", "size": 1.0}, {"id": 450, "source": "réaction", "target": "face", "size": 1.0}, {"id": 451, "source": "réaction", "target": "vidéo", "size": 1.0}, {"id": 452, "source": "récit", "target": "jean", "size": 1.0}, {"id": 453, "source": "réforme", "target": "service", "size": 1.0}, {"id": 454, "source": "région", "target": "face", "size": 1.0}, {"id": 455, "source": "région", "target": "vacance", "size": 1.0}, {"id": 456, "source": "réunion", "target": "ue", "size": 1.0}, {"id": 457, "source": "rêve", "target": "ligue", "size": 1.0}, {"id": 458, "source": "saison", "target": "lundi", "size": 1.0}, {"id": 459, "source": "secret", "target": "famille", "size": 1.0}, {"id": 460, "source": "secret", "target": "trudy", "size": 1.0}, {"id": 461, "source": "semaine", "target": "temps", "size": 1.0}, {"id": 462, "source": "semaine", "target": "vacance", "size": 1.0}, {"id": 463, "source": "service", "target": "chaleur", "size": 1.0}, {"id": 464, "source": "site", "target": "baignade", "size": 1.0}, {"id": 465, "source": "situation", "target": "lundi", "size": 1.0}, {"id": 466, "source": "sommet", "target": "alaska", "size": 1.0}, {"id": 467, "source": "story", "target": "canicule", "size": 1.0}, {"id": 468, "source": "story", "target": "jour", "size": 1.0}, {"id": 469, "source": "story", "target": "sommet", "size": 1.0}, {"id": 470, "source": "sud", "target": "france", "size": 1.0}, {"id": 471, "source": "sud", "target": "nuit", "size": 1.0}, {"id": 472, "source": "suppression", "target": "emploi", "size": 1.0}, {"id": 473, "source": "syndicat", "target": "censure", "size": 1.0}, {"id": 474, "source": "taureau", "target": "tour", "size": 1.0}, {"id": 475, "source": "temps", "target": "record", "size": 1.0}, {"id": 476, "source": "temps", "target": "ukraine", "size": 1.0}, {"id": 477, "source": "territoire", "target": "mise", "size": 1.0}, {"id": 478, "source": "territoire", "target": "russie", "size": 1.0}, {"id": 479, "source": "thay", "target": "garde", "size": 1.0}, {"id": 480, "source": "thriller", "target": "action", "size": 1.0}, {"id": 481, "source": "toulouse", "target": "affaire", "size": 1.0}, {"id": 482, "source": "toulouse", "target": "habitant", "size": 1.0}, {"id": 483, "source": "toulouse", "target": "paris", "size": 1.0}, {"id": 484, "source": "tour", "target": "homme", "size": 1.0}, {"id": 485, "source": "touriste", "target": "euro", "size": 1.0}, {"id": 486, "source": "travail", "target": "aude", "size": 1.0}, {"id": 487, "source": "travail", "target": "fact", "size": 1.0}, {"id": 488, "source": "trudy", "target": "piste", "size": 1.0}, {"id": 489, "source": "trump", "target": "armée", "size": 1.0}, {"id": 490, "source": "trump", "target": "europe", "size": 1.0}, {"id": 491, "source": "trump", "target": "européen", "size": 1.0}, {"id": 492, "source": "trump", "target": "histoire", "size": 1.0}, {"id": 493, "source": "trump", "target": "jour", "size": 1.0}, {"id": 494, "source": "trump", "target": "monde", "size": 1.0}, {"id": 495, "source": "trump", "target": "paix", "size": 1.0}, {"id": 496, "source": "trump", "target": "rencontre", "size": 1.0}, {"id": 497, "source": "trump", "target": "ue", "size": 1.0}, {"id": 498, "source": "trump", "target": "ukraine", "size": 1.0}, {"id": 499, "source": "trump", "target": "ville", "size": 1.0}, {"id": 500, "source": "trump", "target": "xi", "size": 1.0}, {"id": 501, "source": "trump", "target": "états-unis", "size": 1.0}, {"id": 502, "source": "trump", "target": "œil", "size": 1.0}, {"id": 503, "source": "turquie", "target": "mort", "size": 1.0}, {"id": 504, "source": "tête", "target": "mort", "size": 1.0}, {"id": 505, "source": "ue", "target": "info", "size": 1.0}, {"id": 506, "source": "ue", "target": "zelensky", "size": 1.0}, {"id": 507, "source": "ukraine", "target": "drone", "size": 1.0}, {"id": 508, "source": "ukraine", "target": "européen", "size": 1.0}, {"id": 509, "source": "ukraine", "target": "histoire", "size": 1.0}, {"id": 510, "source": "ukraine", "target": "rencontre", "size": 1.0}, {"id": 511, "source": "ukraine", "target": "réunion", "size": 1.0}, {"id": 512, "source": "ukraine", "target": "états-unis", "size": 1.0}, {"id": 513, "source": "uni", "target": "groupe", "size": 1.0}, {"id": 514, "source": "vacance", "target": "mer", "size": 1.0}, {"id": 515, "source": "vacance", "target": "raison", "size": 1.0}, {"id": 516, "source": "vent", "target": "canicule", "size": 1.0}, {"id": 517, "source": "vent", "target": "feu", "size": 1.0}, {"id": 518, "source": "victime", "target": "justice", "size": 1.0}, {"id": 519, "source": "victoire", "target": "pauline", "size": 1.0}, {"id": 520, "source": "victoire", "target": "poutine", "size": 1.0}, {"id": 521, "source": "vie", "target": "maison", "size": 1.0}, {"id": 522, "source": "vie", "target": "région", "size": 1.0}, {"id": 523, "source": "vie", "target": "vie", "size": 1.0}, {"id": 524, "source": "vigilance", "target": "geste", "size": 1.0}, {"id": 525, "source": "vigilance", "target": "journée", "size": 1.0}, {"id": 526, "source": "village", "target": "fils", "size": 1.0}, {"id": 527, "source": "ville", "target": "france", "size": 1.0}, {"id": 528, "source": "ville", "target": "migrant", "size": 1.0}, {"id": 529, "source": "ville", "target": "washington", "size": 1.0}, {"id": 530, "source": "voiture", "target": "entreprise", "size": 1.0}, {"id": 531, "source": "voiture", "target": "prix", "size": 1.0}, {"id": 532, "source": "voyage", "target": "euro", "size": 1.0}, {"id": 533, "source": "voyage", "target": "ia", "size": 1.0}, {"id": 534, "source": "voyage", "target": "touriste", "size": 1.0}, {"id": 535, "source": "végétation", "target": "flamme", "size": 1.0}, {"id": 536, "source": "végétation", "target": "mort", "size": 1.0}, {"id": 537, "source": "vérité", "target": "an", "size": 1.0}, {"id": 538, "source": "vérité", "target": "taureau", "size": 1.0}, {"id": 539, "source": "washington", "target": "donald", "size": 1.0}, {"id": 540, "source": "zelensky", "target": "alaska", "size": 1.0}, {"id": 541, "source": "zelensky", "target": "garde", "size": 1.0}, {"id": 542, "source": "zelensky", "target": "mercredi", "size": 1.0}, {"id": 543, "source": "zelensky", "target": "question", "size": 1.0}, {"id": 544, "source": "zelensky", "target": "territoire", "size": 1.0}, {"id": 545, "source": "âge", "target": "site", "size": 1.0}, {"id": 546, "source": "économie", "target": "an", "size": 1.0}, {"id": 547, "source": "électricité", "target": "raison", "size": 1.0}, {"id": 548, "source": "électricité", "target": "royaume", "size": 1.0}, {"id": 549, "source": "élu", "target": "an", "size": 1.0}, {"id": 550, "source": "élu", "target": "face", "size": 1.0}, {"id": 551, "source": "élu", "target": "gouvernement", "size": 1.0}, {"id": 552, "source": "état", "target": "palestine", "size": 1.0}, {"id": 553, "source": "états-unis", "target": "droit", "size": 1.0}, {"id": 554, "source": "états-unis", "target": "loi", "size": 1.0}, {"id": 555, "source": "états-unis", "target": "rencontre", "size": 1.0}, {"id": 556, "source": "œil", "target": "nuit", "size": 1.0}, {"id": 557, "source": "œil", "target": "œil", "size": 1.0}]